cherno/__init__.py
cherno/__main__.py
cherno/exceptions.py
cherno/extraction.py
cherno/guider.py
cherno/lcotcc.py
cherno/maskbits.py
cherno/tcc.py
cherno/utils.py
cherno/actor/__init__.py
cherno/actor/actor.py
cherno/actor/exposer.py
cherno/actor/commands/__init__.py
cherno/actor/commands/acquire.py
cherno/actor/commands/config.py
cherno/actor/commands/guide.py
cherno/actor/commands/offset.py
cherno/actor/commands/reprocess.py
cherno/actor/commands/scale.py
cherno/actor/commands/set.py
cherno/actor/commands/show.py
cherno/actor/commands/status.py
cherno/actor/commands/stop.py
cherno/actor/commands/version.py
cherno/etc/astrometrynet_APO.cfg
cherno/etc/astrometrynet_LCO.cfg
cherno/etc/cherno_APO.yml
cherno/etc/cherno_LCO.yml
cherno/etc/schema.json
sdss_cherno-1.2.1.dist-info/METADATA
sdss_cherno-1.2.1.dist-info/WHEEL
sdss_cherno-1.2.1.dist-info/entry_points.txt
sdss_cherno-1.2.1.dist-info/licenses/LICENSE.md
sdss_cherno-1.2.1.dist-info/RECORD
