Metadata-Version: 2.4
Name: sdss-cherno
Version: 1.2.1
Summary: SDSS guider actor
Project-URL: Homepage, https://github.com/sdss/cherno
Project-URL: Repository, https://github.com/sdss/cherno
Project-URL: Documentation, https://sdss-cherno.readthedocs.org
Author-email: José Sánchez-Gallego <gallegoj@uw.edu>
License-Expression: BSD-3-Clause
License-File: LICENSE.md
Requires-Python: >=3.10
Requires-Dist: astropy>=6.0.0
Requires-Dist: click-default-group>=1.2.2
Requires-Dist: click<8.2.0,>=8.0.0
Requires-Dist: contourpy<=1.3.2
Requires-Dist: numexpr<2.11.0
Requires-Dist: numpy<2.0.0,>1
Requires-Dist: pandas>=2.0.0
Requires-Dist: psycopg2-binary>=2.9.5
Requires-Dist: pyarrow<=20.0.0
Requires-Dist: sdss-clu>=1.8.0
Requires-Dist: sdss-coordio>=1.11.2
Requires-Dist: sdsstools>=1.5.5
Requires-Dist: simple-pid>=1.0.1
Requires-Dist: sqlalchemy>=2.0.0
Requires-Dist: tables
